ax25/__init__.py
ax25/netrom.py
ax25/ports.py
ax25/socket.py
pyham_ax25-1.0.3.dist-info/LICENSE
pyham_ax25-1.0.3.dist-info/WHEEL
pyham_ax25-1.0.3.dist-info/METADATA
pyham_ax25-1.0.3.dist-info/RECORD
