Metadata-Version: 2.1
Name: pyham_ax25
Version: 1.0.3
Summary: AX.25 Frame Encoding and Decoding & Socket Support
Keywords: ham radio,amateur radio,packet radio,AX.25,AX25,APRS,NET/ROM,NETROM,protocol
Author-email: Martin F N Cooper <mfncooper@gmail.com>
Requires-Python: >=3.7
Classifier: Development Status :: 5 - Production/Stable
Classifier: Intended Audience :: Developers
Classifier: License :: OSI Approved :: MIT License
Classifier: Programming Language :: Python :: 3 :: Only
Classifier: Topic :: Communications :: Ham Radio
Project-URL: Change Log, https://github.com/mfncooper/pyham_ax25/blob/main/CHANGELOG.md
Project-URL: Documentation, https://pyham-ax25.readthedocs.io
Project-URL: Source Code, https://github.com/mfncooper/pyham_ax25
